rtl/counter.sv
// Small learning block used before the cryptographic RTL milestones.
module counter #(
    parameter int unsigned WIDTH = 4
) (
    input  logic                  clk,
    input  logic                  rst_n,
    input  logic                  enable,
    output logic [WIDTH-1:0]      count
);

    always_ff @(posedge clk) begin
        if (!rst_n) begin
            count <= '0;
        end else if (enable) begin
            count <= count + 1'b1;
        end
    end

endmodule

tb/tb_counter.sv
`timescale 1ns/1ps

module tb_counter;
    localparam int unsigned WIDTH = 4;

    logic clk = 1'b0;
    logic rst_n = 1'b0;
    logic enable = 1'b0;
    logic [WIDTH-1:0] count;

    counter #(.WIDTH(WIDTH)) dut (
        .clk(clk),
        .rst_n(rst_n),
        .enable(enable),
        .count(count)
    );

    always #5 clk = ~clk;

    task automatic expect_count(input logic [WIDTH-1:0] expected);
        if (count !== expected) begin
            $error("count mismatch: got %0d expected %0d", count, expected);
            $fatal(1);
        end
    endtask

    initial begin
        $dumpfile("sim/counter.vcd");
        $dumpvars(0, tb_counter);

        // Synchronous reset is sampled on a rising clock edge.
        @(posedge clk);
        #1;
        expect_count(4'd0);

        rst_n = 1'b1;
        enable = 1'b1;
        @(posedge clk);
        #1;
        expect_count(4'd1);

        enable = 1'b0;
        @(posedge clk);
        #1;
        expect_count(4'd1);

        enable = 1'b1;
        repeat (14) begin
            @(posedge clk);
            #1;
        end
        expect_count(4'd15);

        @(posedge clk);
        #1;
        expect_count(4'd0);

        rst_n = 1'b0;
        @(posedge clk);
        #1;
        expect_count(4'd0);

        $display("PASS: counter reset, enable, hold, and wrap checks");
        $finish;
    end
endmodule

sim/counter.vcd
$date
	Tue Oct 06 21:12:12 2026
$end
$version
	Icarus Verilog
$end
$timescale
	1ps
$end
$scope module tb_counter $end
$var wire 4 ! count [3:0] $end
$var parameter 32 " WIDTH $end
$var reg 1 # clk $end
$var reg 1 $ enable $end
$var reg 1 % rst_n $end
$scope module dut $end
$var wire 1 # clk $end
$var wire 1 $ enable $end
$var wire 1 % rst_n $end
$var parameter 32 & WIDTH $end
$var reg 4 ' count [3:0] $end
$upscope $end
$scope task expect_count $end
$upscope $end
$upscope $end
$enddefinitions $end
$comment Show the parameter values. $end
$dumpall
b100 &
b100 "
$end
#0
$dumpvars
bx '
0%
0$
0#
bx !
$end
#5000
b0 !
b0 '
1#
#6000
1$
1%
#10000
0#
#15000
b1 !
b1 '
1#
#16000
0$
#20000
0#
#25000
1#
#26000
1$
#30000
0#
#35000
b10 !
b10 '
1#
#40000
0#
#45000
b11 !
b11 '
1#
#50000
0#
#55000
b100 !
b100 '
1#
#60000
0#
#65000
b101 !
b101 '
1#
#70000
0#
#75000
b110 !
b110 '
1#
#80000
0#
#85000
b111 !
b111 '
1#
#90000
0#
#95000
b1000 !
b1000 '
1#
#100000
0#
#105000
b1001 !
b1001 '
1#
#110000
0#
#115000
b1010 !
b1010 '
1#
#120000
0#
#125000
b1011 !
b1011 '
1#
#130000
0#
#135000
b1100 !
b1100 '
1#
#140000
0#
#145000
b1101 !
b1101 '
1#
#150000
0#
#155000
b1110 !
b1110 '
1#
#160000
0#
#165000
b1111 !
b1111 '
1#
#170000
0#
#175000
b0 !
b0 '
1#
#176000
0%
