rtl/authentication_guard.sv
// Stores the authentication decision and gates decryption plaintext release.
module authentication_guard (
    input  logic clk,
    input  logic rst_n,
    input  logic clear,
    input  logic decrypt,
    input  logic decision_valid,
    input  logic tag_match,
    output logic auth_result_valid,
    output logic accept,
    output logic reject,
    output logic plaintext_allowed
);
    always_ff @(posedge clk) begin
        if (!rst_n) begin
            auth_result_valid <= 1'b0;
            accept <= 1'b0;
            reject <= 1'b0;
            plaintext_allowed <= 1'b0;
        end else if (clear) begin
            auth_result_valid <= 1'b0;
            accept <= 1'b0;
            reject <= 1'b0;
            plaintext_allowed <= 1'b0;
        end else if (decision_valid && decrypt) begin
            auth_result_valid <= 1'b1;
            accept <= tag_match;
            reject <= !tag_match;
            plaintext_allowed <= tag_match;
        end
    end
endmodule

rtl/tag_verifier.sv
// Pembanding tag 128-bit terdaftar.
// start menangkap calculated_tag dan received_tag; done kemudian berpulsa
// bersama match atau mismatch. Controller memakai hasilnya untuk mengizinkan
// atau menolak pelepasan plaintext dekripsi.
module tag_verifier (
    input  logic         clk,
    input  logic         rst_n,
    input  logic         start,
    input  logic [127:0] calculated_tag,
    input  logic [127:0] received_tag,
    output logic         busy,
    output logic         done,
    output logic         match,
    output logic         mismatch
);
    logic [127:0] calculated_latched;
    logic [127:0] received_latched;
    logic compare_pending;

    // Snapshot kedua tag mencegah perubahan input setelah start mengubah
    // keputusan. XOR dan reduksi membandingkan seluruh 128 bit.
    always_ff @(posedge clk) begin
        if (!rst_n) begin
            calculated_latched <= '0;
            received_latched <= '0;
            compare_pending <= 1'b0;
            busy <= 1'b0;
            done <= 1'b0;
            match <= 1'b0;
            mismatch <= 1'b0;
        end else begin
            done <= 1'b0;
            match <= 1'b0;
            mismatch <= 1'b0;

            if (start && !busy) begin
                calculated_latched <= calculated_tag;
                received_latched <= received_tag;
                compare_pending <= 1'b1;
                busy <= 1'b1;
            end else if (compare_pending) begin
                compare_pending <= 1'b0;
                busy <= 1'b0;
                done <= 1'b1;
                if ((calculated_latched ^ received_latched) == 128'b0)
                    match <= 1'b1;
                else
                    mismatch <= 1'b1;
            end
        end
    end
endmodule

rtl/tag_generator.sv
// Register handshake untuk menahan tag akhir yang dihitung core.
// tag_valid/tag_out tetap stabil selama tag_ready rendah dan dibersihkan
// setelah transfer atau reset. Modul ini tidak menghitung tag kriptografi.
module tag_generator (
    input  logic         clk,
    input  logic         rst_n,
    input  logic         load,
    input  logic [127:0] tag_in,
    output logic         tag_valid,
    input  logic         tag_ready,
    output logic [127:0] tag_out
);
    // Tag baru boleh dimuat jika slot kosong atau tag lama dikonsumsi pada
    // siklus yang sama, sehingga data valid tidak tertimpa saat tertahan.
    always_ff @(posedge clk) begin
        if (!rst_n) begin
            tag_valid <= 1'b0;
            tag_out <= '0;
        end else begin
            if (tag_valid && tag_ready)
                tag_valid <= 1'b0;

            if (load && (!tag_valid || tag_ready)) begin
                tag_out <= tag_in;
                tag_valid <= 1'b1;
            end
        end
    end
endmodule

tb/tb_tag_auth_modules.sv
`timescale 1ns/1ps

// Testbench unit pembentuk tag, verifier, dan guard. Menguji penahanan tag
// saat backpressure, tag cocok/tidak cocok, keputusan ACCEPT/REJECT, clear, reset.
module tb_tag_auth_modules;
    logic clk = 1'b0;
    logic rst_n = 1'b0;

    logic tag_load = 1'b0;
    logic [127:0] tag_in = '0;
    logic tag_valid;
    logic tag_ready = 1'b0;
    logic [127:0] tag_out;

    logic verify_start = 1'b0;
    logic [127:0] calculated_tag = '0;
    logic [127:0] received_tag = '0;
    logic verify_busy;
    logic verify_done;
    logic tag_match;
    logic tag_mismatch;

    logic guard_clear = 1'b0;
    logic decrypt = 1'b0;
    logic decision_valid = 1'b0;
    logic decision_match = 1'b0;
    logic auth_result_valid;
    logic accept;
    logic reject;
    logic plaintext_allowed;

    tag_generator generator (
        .clk(clk), .rst_n(rst_n), .load(tag_load), .tag_in(tag_in),
        .tag_valid(tag_valid), .tag_ready(tag_ready), .tag_out(tag_out)
    );

    tag_verifier verifier (
        .clk(clk), .rst_n(rst_n), .start(verify_start),
        .calculated_tag(calculated_tag), .received_tag(received_tag),
        .busy(verify_busy), .done(verify_done), .match(tag_match),
        .mismatch(tag_mismatch)
    );

    authentication_guard guard_unit (
        .clk(clk), .rst_n(rst_n), .clear(guard_clear), .decrypt(decrypt),
        .decision_valid(decision_valid), .tag_match(decision_match),
        .auth_result_valid(auth_result_valid), .accept(accept), .reject(reject),
        .plaintext_allowed(plaintext_allowed)
    );

    always #5 clk = ~clk;

    task automatic tick;
        begin
            // Tunggu tepi clock aktif dan beri waktu bagi assignment nonblocking.
            @(posedge clk);
            #1;
        end
    endtask

    initial begin
        $dumpfile("sim/tag_auth_modules.vcd");
        $dumpvars(0, tb_tag_auth_modules);

        tick();
        if (tag_valid || tag_out !== 128'b0 || verify_busy || verify_done ||
            tag_match || tag_mismatch || auth_result_valid || accept || reject || plaintext_allowed)
            $fatal(1, "synchronous reset did not clear tag/authentication modules");
        rst_n = 1'b1;

        // Tag harus tetap stabil ketika penerima menahan ready rendah.
        @(negedge clk);
        tag_in = 128'h00112233445566778899aabbccddeeff;
        tag_load = 1'b1;
        tick();
        tag_load = 1'b0;
        if (!tag_valid || tag_out !== 128'h00112233445566778899aabbccddeeff)
            $fatal(1, "tag generator failed to capture a tag");
        @(negedge clk);
        tag_in = 128'hffeeddccbbaa99887766554433221100;
        tag_load = 1'b1;
        tick();
        tag_load = 1'b0;
        if (!tag_valid || tag_out !== 128'h00112233445566778899aabbccddeeff)
            $fatal(1, "tag generator changed its output while stalled");

        // Konsumsi dan pemuatan serentak mengganti tag tanpa jeda valid.
        @(negedge clk);
        tag_ready = 1'b1;
        tag_load = 1'b1;
        tick();
        tag_ready = 1'b0;
        tag_load = 1'b0;
        if (!tag_valid || tag_out !== 128'hffeeddccbbaa99887766554433221100)
            $fatal(1, "tag generator did not replace a consumed tag");
        @(negedge clk);
        tag_ready = 1'b1;
        tick();
        tag_ready = 1'b0;
        if (tag_valid)
            $fatal(1, "tag generator did not clear valid after handshake");

        // Verifier harus membandingkan snapshot, bukan input yang berubah sesudah start.
        @(negedge clk);
        calculated_tag = 128'h112233445566778899aabbccddeeff00;
        received_tag = calculated_tag;
        verify_start = 1'b1;
        tick();
        verify_start = 1'b0;
        if (!verify_busy || verify_done || tag_match || tag_mismatch)
            $fatal(1, "tag verifier did not enter its compare phase");
        calculated_tag = '0;
        received_tag = '1;
        tick();
        if (verify_busy || !verify_done || !tag_match || tag_mismatch)
            $fatal(1, "tag verifier did not report a match from latched values");
        tick();
        if (verify_done || tag_match || tag_mismatch)
            $fatal(1, "tag verifier result was not a one-cycle pulse");

        // Perbedaan satu bit di bagian mana pun dari tag harus ditolak.
        @(negedge clk);
        calculated_tag = 128'b0;
        received_tag = 128'h80000000000000000000000000000000;
        verify_start = 1'b1;
        tick();
        verify_start = 1'b0;
        tick();
        if (!verify_done || tag_match || !tag_mismatch)
            $fatal(1, "tag verifier failed to detect a high-order tag mismatch");
        tick();

        // Guard mengabaikan keputusan enkripsi dan belum boleh membuka output.
        @(negedge clk);
        decrypt = 1'b1;
        decision_match = 1'b1;
        decision_valid = 1'b0;
        tick();
        if (auth_result_valid || accept || reject || plaintext_allowed)
            $fatal(1, "guard exposed plaintext before a valid decision");
        @(negedge clk);
        decrypt = 1'b0;
        decision_valid = 1'b1;
        tick();
        if (auth_result_valid || accept || reject || plaintext_allowed)
            $fatal(1, "guard incorrectly processed an encryption decision");

        // Keputusan dekripsi valid membuka plaintext dan bertahan sampai clear.
        @(negedge clk);
        decrypt = 1'b1;
        decision_match = 1'b1;
        tick();
        decision_valid = 1'b0;
        if (!auth_result_valid || !accept || reject || !plaintext_allowed)
            $fatal(1, "guard failed to accept authenticated plaintext");
        tick();
        if (!auth_result_valid || !accept || reject || !plaintext_allowed)
            $fatal(1, "guard did not hold the accepted decision");

        // Hapus keputusan sebelumnya, lalu periksa autentikasi yang tidak valid.
        @(negedge clk);
        guard_clear = 1'b1;
        tick();
        guard_clear = 1'b0;
        if (auth_result_valid || accept || reject || plaintext_allowed)
            $fatal(1, "guard clear did not revoke the prior decision");
        @(negedge clk);
        decision_match = 1'b0;
        decision_valid = 1'b1;
        tick();
        decision_valid = 1'b0;
        if (!auth_result_valid || accept || !reject || plaintext_allowed)
            $fatal(1, "guard failed to reject unauthenticated plaintext");

        @(negedge clk);
        rst_n = 1'b0;
        tick();
        if (auth_result_valid || accept || reject || plaintext_allowed ||
            tag_valid || verify_busy || verify_done)
            $fatal(1, "reset did not revoke visible module state");

        $display("PASS: tag generator handshake, full-width tag verifier, and authentication guard checks");
        $finish;
    end
endmodule

sim/tag_auth_modules.vcd
$date
	Tue Oct 06 21:12:17 2026
$end
$version
	Icarus Verilog
$end
$timescale
	1ps
$end
$scope module tb_tag_auth_modules $end
$var wire 1 ! verify_done $end
$var wire 1 " verify_busy $end
$var wire 1 # tag_valid $end
$var wire 128 $ tag_out [127:0] $end
$var wire 1 % tag_mismatch $end
$var wire 1 & tag_match $end
$var wire 1 ' reject $end
$var wire 1 ( plaintext_allowed $end
$var wire 1 ) auth_result_valid $end
$var wire 1 * accept $end
$var reg 128 + calculated_tag [127:0] $end
$var reg 1 , clk $end
$var reg 1 - decision_match $end
$var reg 1 . decision_valid $end
$var reg 1 / decrypt $end
$var reg 1 0 guard_clear $end
$var reg 128 1 received_tag [127:0] $end
$var reg 1 2 rst_n $end
$var reg 128 3 tag_in [127:0] $end
$var reg 1 4 tag_load $end
$var reg 1 5 tag_ready $end
$var reg 1 6 verify_start $end
$scope module generator $end
$var wire 1 , clk $end
$var wire 1 4 load $end
$var wire 1 2 rst_n $end
$var wire 128 7 tag_in [127:0] $end
$var wire 1 5 tag_ready $end
$var reg 128 8 tag_out [127:0] $end
$var reg 1 # tag_valid $end
$upscope $end
$scope module guard_unit $end
$var wire 1 0 clear $end
$var wire 1 , clk $end
$var wire 1 . decision_valid $end
$var wire 1 / decrypt $end
$var wire 1 2 rst_n $end
$var wire 1 - tag_match $end
$var reg 1 * accept $end
$var reg 1 ) auth_result_valid $end
$var reg 1 ( plaintext_allowed $end
$var reg 1 ' reject $end
$upscope $end
$scope module verifier $end
$var wire 128 9 calculated_tag [127:0] $end
$var wire 1 , clk $end
$var wire 128 : received_tag [127:0] $end
$var wire 1 2 rst_n $end
$var wire 1 6 start $end
$var reg 1 " busy $end
$var reg 128 ; calculated_latched [127:0] $end
$var reg 1 < compare_pending $end
$var reg 1 ! done $end
$var reg 1 & match $end
$var reg 1 % mismatch $end
$var reg 128 = received_latched [127:0] $end
$upscope $end
$scope task tick $end
$upscope $end
$upscope $end
$enddefinitions $end
$comment Show the parameter values. $end
$dumpall
$end
#0
$dumpvars
bx =
x<
bx ;
b0 :
b0 9
bx 8
b0 7
06
05
04
b0 3
02
b0 1
00
0/
0.
0-
0,
b0 +
x*
x)
x(
x'
x&
x%
bx $
x#
x"
x!
$end
#5000
b0 $
b0 8
0#
0%
0&
0!
0"
0<
b0 =
b0 ;
0(
0'
0*
0)
1,
#6000
12
#10000
14
b100010010001000110011010001000101010101100110011101111000100010011001101010101011101111001100110111011110111011111111 3
b100010010001000110011010001000101010101100110011101111000100010011001101010101011101111001100110111011110111011111111 7
0,
#15000
1#
b100010010001000110011010001000101010101100110011101111000100010011001101010101011101111001100110111011110111011111111 $
b100010010001000110011010001000101010101100110011101111000100010011001101010101011101111001100110111011110111011111111 8
1,
#16000
04
#20000
14
b11111111111011101101110111001100101110111010101010011001100010000111011101100110010101010100010000110011001000100001000100000000 3
b11111111111011101101110111001100101110111010101010011001100010000111011101100110010101010100010000110011001000100001000100000000 7
0,
#25000
1,
#26000
04
#30000
14
15
0,
#35000
b11111111111011101101110111001100101110111010101010011001100010000111011101100110010101010100010000110011001000100001000100000000 $
b11111111111011101101110111001100101110111010101010011001100010000111011101100110010101010100010000110011001000100001000100000000 8
1#
1,
#36000
04
05
#40000
15
0,
#45000
0#
1,
#46000
05
#50000
16
b10001001000100011001101000100010101010110011001110111100010001001100110101010101110111100110011011101111011101111111100000000 1
b10001001000100011001101000100010101010110011001110111100010001001100110101010101110111100110011011101111011101111111100000000 :
b10001001000100011001101000100010101010110011001110111100010001001100110101010101110111100110011011101111011101111111100000000 +
b10001001000100011001101000100010101010110011001110111100010001001100110101010101110111100110011011101111011101111111100000000 9
0,
#55000
1"
1<
b10001001000100011001101000100010101010110011001110111100010001001100110101010101110111100110011011101111011101111111100000000 =
b10001001000100011001101000100010101010110011001110111100010001001100110101010101110111100110011011101111011101111111100000000 ;
1,
#56000
b11111111111111111111111111111111111111111111111111111111111111111111111111111111111111111111111111111111111111111111111111111111 1
b11111111111111111111111111111111111111111111111111111111111111111111111111111111111111111111111111111111111111111111111111111111 :
b0 +
b0 9
06
#60000
0,
#65000
1&
1!
0"
0<
1,
#70000
0,
#75000
0&
0!
1,
#80000
16
b10000000000000000000000000000000000000000000000000000000000000000000000000000000000000000000000000000000000000000000000000000000 1
b10000000000000000000000000000000000000000000000000000000000000000000000000000000000000000000000000000000000000000000000000000000 :
0,
#85000
1"
1<
b10000000000000000000000000000000000000000000000000000000000000000000000000000000000000000000000000000000000000000000000000000000 =
b0 ;
1,
#86000
06
#90000
0,
#95000
1%
1!
0"
0<
1,
#100000
0,
#105000
0%
0!
1,
#110000
1-
1/
0,
#115000
1,
#120000
1.
0/
0,
#125000
1,
#130000
1/
0,
#135000
1(
1*
1)
1,
#136000
0.
#140000
0,
#145000
1,
#150000
10
0,
#155000
0(
0*
0)
1,
#156000
00
#160000
1.
0-
0,
#165000
1'
1)
1,
#166000
0.
#170000
02
0,
#175000
0'
0)
b0 =
b0 $
b0 8
1,
